<time>
<datatime>2018-06</datatime>
<location>
<locationname>BANQIAO,板橋</locationname>
<stationid>466880</stationid>
<weatherelement>
<elementname>平均溫度</elementname>
<elementvalue>
<value>28.3</value>
</elementvalue>
</weatherelement>
<weatherelement>
<elementname>最高溫度</elementname>
<elementvalue>
<value>36.1</value>
</elementvalue>
</weatherelement>
<weatherelement>
<elementname>最高溫度日期</elementname>
<elementvalue>
<value>28</value>
</elementvalue>
</weatherelement>
<weatherelement>
<elementname>最低溫度</elementname>
<elementvalue>
<value>21.9</value>
</elementvalue>
</weatherelement>
<weatherelement>
<elementname>最低溫度日期</elementname>
<elementvalue>
<value>12</value>
</elementvalue>
</weatherelement>
<weatherelement>
<elementname>降水量</elementname>
<elementvalue>
<value>46.1</value>
</elementvalue>
</weatherelement>
<weatherelement>
<elementname>最大10分鐘風風速</elementname>
<elementvalue>
<value>7.1</value>
</elementvalue>
</weatherelement>
<weatherelement>
<elementname>最大10分鐘風風向</elementname>
<elementvalue>
<value>220.0</value>
</elementvalue>
</weatherelement>
<weatherelement>
<elementname>最大10分鐘風日期</elementname>
<elementvalue>
<value>23</value>
</elementvalue>
</weatherelement>
<weatherelement>
<elementname>最大瞬間風風速</elementname>
<elementvalue>
<value>14.4</value>
</elementvalue>
</weatherelement>
<weatherelement>
<elementname>最大瞬間風風向</elementname>
<elementvalue>
<value>210.0</value>
</elementvalue>
</weatherelement>
<weatherelement>
<elementname>最大瞬間風日期</elementname>
<elementvalue>
<value>19</value>
</elementvalue>
</weatherelement>
<weatherelement>
<elementname>平均相對濕度</elementname>
<elementvalue>
<value>75</value>
</elementvalue>
</weatherelement>
<weatherelement>
<elementname>最小相對濕度</elementname>
<elementvalue>
<value>43</value>
</elementvalue>
</weatherelement>
<weatherelement>
<elementname>最小相對濕度日期</elementname>
<elementvalue>
<value>12</value>
</elementvalue>
</weatherelement>
<weatherelement>
<elementname>測站氣壓</elementname>
<elementvalue>
<value>1004.8</value>
</elementvalue>
</weatherelement>
<weatherelement>
<elementname>降水日數</elementname>
<elementvalue>
<value>11</value>
</elementvalue>
</weatherelement>
<weatherelement>
<elementname>日照時數</elementname>
<elementvalue>
<value>142.0</value>
</elementvalue>
</weatherelement>
</location>
<location>
<locationname>TAMSUI,淡水</locationname>
<stationid>466900</stationid>
<weatherelement>
<elementname>平均溫度</elementname>
<elementvalue>
<value>28.0</value>
</elementvalue>
</weatherelement>
<weatherelement>
<elementname>最高溫度</elementname>
<elementvalue>
<value>36.5</value>
</elementvalue>
</weatherelement>
<weatherelement>
<elementname>最高溫度日期</elementname>
<elementvalue>
<value>7</value>
</elementvalue>
</weatherelement>
<weatherelement>
<elementname>最低溫度</elementname>
<elementvalue>
<value>21.0</value>
</elementvalue>
</weatherelement>
<weatherelement>
<elementname>最低溫度日期</elementname>
<elementvalue>
<value>12</value>
</elementvalue>
</weatherelement>
<weatherelement>
<elementname>降水量</elementname>
<elementvalue>
<value>42.0</value>
</elementvalue>
</weatherelement>
<weatherelement>
<elementname>最大10分鐘風風速</elementname>
<elementvalue>
<value>5.4</value>
</elementvalue>
</weatherelement>
<weatherelement>
<elementname>最大10分鐘風風向</elementname>
<elementvalue>
<value>20.0</value>
</elementvalue>
</weatherelement>
<weatherelement>
<elementname>最大10分鐘風日期</elementname>
<elementvalue>
<value>11</value>
</elementvalue>
</weatherelement>
<weatherelement>
<elementname>最大瞬間風風速</elementname>
<elementvalue>
<value>15.3</value>
</elementvalue>
</weatherelement>
<weatherelement>
<elementname>最大瞬間風風向</elementname>
<elementvalue>
<value>120.0</value>
</elementvalue>
</weatherelement>
<weatherelement>
<elementname>最大瞬間風日期</elementname>
<elementvalue>
<value>13</value>
</elementvalue>
</weatherelement>
<weatherelement>
<elementname>平均相對濕度</elementname>
<elementvalue>
<value>75</value>
</elementvalue>
</weatherelement>
<weatherelement>
<elementname>最小相對濕度</elementname>
<elementvalue>
<value>29</value>
</elementvalue>
</weatherelement>
<weatherelement>
<elementname>最小相對濕度日期</elementname>
<elementvalue>
<value>12</value>
</elementvalue>
</weatherelement>
<weatherelement>
<elementname>測站氣壓</elementname>
<elementvalue>
<value>1004.3</value>
</elementvalue>
</weatherelement>
<weatherelement>
<elementname>降水日數</elementname>
<elementvalue>
<value>6</value>
</elementvalue>
</weatherelement>
<weatherelement>
<elementname>日照時數</elementname>
<elementvalue>
<value>166.5</value>
</elementvalue>
</weatherelement>
</location>
<location>
<locationname>ANBU,鞍部</locationname>
<stationid>466910</stationid>
<weatherelement>
<elementname>平均溫度</elementname>
<elementvalue>
<value>21.9</value>
</elementvalue>
</weatherelement>
<weatherelement>
<elementname>最高溫度</elementname>
<elementvalue>
<value>28.3</value>
</elementvalue>
</weatherelement>
<weatherelement>
<elementname>最高溫度日期</elementname>
<elementvalue>
<value>26</value>
</elementvalue>
</weatherelement>
<weatherelement>
<elementname>最低溫度</elementname>
<elementvalue>
<value>15.3</value>
</elementvalue>
</weatherelement>
<weatherelement>
<elementname>最低溫度日期</elementname>
<elementvalue>
<value>1</value>
</elementvalue>
</weatherelement>
<weatherelement>
<elementname>降水量</elementname>
<elementvalue>
<value>152.2</value>
</elementvalue>
</weatherelement>
<weatherelement>
<elementname>最大10分鐘風風速</elementname>
<elementvalue>
<value>9.7</value>
</elementvalue>
</weatherelement>
<weatherelement>
<elementname>最大10分鐘風風向</elementname>
<elementvalue>
<value>360.0</value>
</elementvalue>
</weatherelement>
<weatherelement>
<elementname>最大10分鐘風日期</elementname>
<elementvalue>
<value>11</value>
</elementvalue>
</weatherelement>
<weatherelement>
<elementname>最大瞬間風風速</elementname>
<elementvalue>
<value>20.1</value>
</elementvalue>
</weatherelement>
<weatherelement>
<elementname>最大瞬間風風向</elementname>
<elementvalue>
<value>350.0</value>
</elementvalue>
</weatherelement>
<weatherelement>
<elementname>最大瞬間風日期</elementname>
<elementvalue>
<value>15</value>
</elementvalue>
</weatherelement>
<weatherelement>
<elementname>平均相對濕度</elementname>
<elementvalue>
<value>89</value>
</elementvalue>
</weatherelement>
<weatherelement>
<elementname>最小相對濕度</elementname>
<elementvalue>
<value>35</value>
</elementvalue>
</weatherelement>
<weatherelement>
<elementname>最小相對濕度日期</elementname>
<elementvalue>
<value>11</value>
</elementvalue>
</weatherelement>
<weatherelement>
<elementname>測站氣壓</elementname>
<elementvalue>
<value>916.1</value>
</elementvalue>
</weatherelement>
<weatherelement>
<elementname>降水日數</elementname>
<elementvalue>
<value>15</value>
</elementvalue>
</weatherelement>
<weatherelement>
<elementname>日照時數</elementname>
<elementvalue>
<value>94.0</value>
</elementvalue>
</weatherelement>
</location>
<location>
<locationname>TAIPEI,臺北</locationname>
<stationid>466920</stationid>
<weatherelement>
<elementname>平均溫度</elementname>
<elementvalue>
<value>28.5</value>
</elementvalue>
</weatherelement>
<weatherelement>
<elementname>最高溫度</elementname>
<elementvalue>
<value>37.8</value>
</elementvalue>
</weatherelement>
<weatherelement>
<elementname>最高溫度日期</elementname>
<elementvalue>
<value>28</value>
</elementvalue>
</weatherelement>
<weatherelement>
<elementname>最低溫度</elementname>
<elementvalue>
<value>22.2</value>
</elementvalue>
</weatherelement>
<weatherelement>
<elementname>最低溫度日期</elementname>
<elementvalue>
<value>1</value>
</elementvalue>
</weatherelement>
<weatherelement>
<elementname>降水量</elementname>
<elementvalue>
<value>119.8</value>
</elementvalue>
</weatherelement>
<weatherelement>
<elementname>最大10分鐘風風速</elementname>
<elementvalue>
<value>7.6</value>
</elementvalue>
</weatherelement>
<weatherelement>
<elementname>最大10分鐘風風向</elementname>
<elementvalue>
<value>80.0</value>
</elementvalue>
</weatherelement>
<weatherelement>
<elementname>最大10分鐘風日期</elementname>
<elementvalue>
<value>1</value>
</elementvalue>
</weatherelement>
<weatherelement>
<elementname>最大瞬間風風速</elementname>
<elementvalue>
<value>14.3</value>
</elementvalue>
</weatherelement>
<weatherelement>
<elementname>最大瞬間風風向</elementname>
<elementvalue>
<value>80.0</value>
</elementvalue>
</weatherelement>
<weatherelement>
<elementname>最大瞬間風日期</elementname>
<elementvalue>
<value>1</value>
</elementvalue>
</weatherelement>
<weatherelement>
<elementname>平均相對濕度</elementname>
<elementvalue>
<value>69</value>
</elementvalue>
</weatherelement>
<weatherelement>
<elementname>最小相對濕度</elementname>
<elementvalue>
<value>36</value>
</elementvalue>
</weatherelement>
<weatherelement>
<elementname>最小相對濕度日期</elementname>
<elementvalue>
<value>12</value>
</elementvalue>
</weatherelement>
<weatherelement>
<elementname>測站氣壓</elementname>
<elementvalue>
<value>1002.5</value>
</elementvalue>
</weatherelement>
<weatherelement>
<elementname>降水日數</elementname>
<elementvalue>
<value>13</value>
</elementvalue>
</weatherelement>
<weatherelement>
<elementname>日照時數</elementname>
<elementvalue>
<value>105.7</value>
</elementvalue>
</weatherelement>
</location>
<location>
<locationname>ZHUZIHU,竹子湖</locationname>
<stationid>466930</stationid>
<weatherelement>
<elementname>平均溫度</elementname>
<elementvalue>
<value>23.6</value>
</elementvalue>
</weatherelement>
<weatherelement>
<elementname>最高溫度</elementname>
<elementvalue>
<value>30.8</value>
</elementvalue>
</weatherelement>
<weatherelement>
<elementname>最高溫度日期</elementname>
<elementvalue>
<value>30</value>
</elementvalue>
</weatherelement>
<weatherelement>
<elementname>最低溫度</elementname>
<elementvalue>
<value>17.4</value>
</elementvalue>
</weatherelement>
<weatherelement>
<elementname>最低溫度日期</elementname>
<elementvalue>
<value>1</value>
</elementvalue>
</weatherelement>
<weatherelement>
<elementname>降水量</elementname>
<elementvalue>
<value>151.0</value>
</elementvalue>
</weatherelement>
<weatherelement>
<elementname>最大10分鐘風風速</elementname>
<elementvalue>
<value>7.8</value>
</elementvalue>
</weatherelement>
<weatherelement>
<elementname>最大10分鐘風風向</elementname>
<elementvalue>
<value>30.0</value>
</elementvalue>
</weatherelement>
<weatherelement>
<elementname>最大10分鐘風日期</elementname>
<elementvalue>
<value>14</value>
</elementvalue>
</weatherelement>
<weatherelement>
<elementname>最大瞬間風風速</elementname>
<elementvalue>
<value>16.9</value>
</elementvalue>
</weatherelement>
<weatherelement>
<elementname>最大瞬間風風向</elementname>
<elementvalue>
<value>20.0</value>
</elementvalue>
</weatherelement>
<weatherelement>
<elementname>最大瞬間風日期</elementname>
<elementvalue>
<value>14</value>
</elementvalue>
</weatherelement>
<weatherelement>
<elementname>平均相對濕度</elementname>
<elementvalue>
<value>83</value>
</elementvalue>
</weatherelement>
<weatherelement>
<elementname>最小相對濕度</elementname>
<elementvalue>
<value>47</value>
</elementvalue>
</weatherelement>
<weatherelement>
<elementname>最小相對濕度日期</elementname>
<elementvalue>
<value>12</value>
</elementvalue>
</weatherelement>
<weatherelement>
<elementname>測站氣壓</elementname>
<elementvalue>
<value>939.2</value>
</elementvalue>
</weatherelement>
<weatherelement>
<elementname>降水日數</elementname>
<elementvalue>
<value>14</value>
</elementvalue>
</weatherelement>
<weatherelement>
<elementname>日照時數</elementname>
<elementvalue>
<value>124.4</value>
</elementvalue>
</weatherelement>
</location>
<location>
<locationname>KEELUNG,基隆</locationname>
<stationid>466940</stationid>
<weatherelement>
<elementname>平均溫度</elementname>
<elementvalue>
<value>27.2</value>
</elementvalue>
</weatherelement>
<weatherelement>
<elementname>最高溫度</elementname>
<elementvalue>
<value>35.5</value>
</elementvalue>
</weatherelement>
<weatherelement>
<elementname>最高溫度日期</elementname>
<elementvalue>
<value>28</value>
</elementvalue>
</weatherelement>
<weatherelement>
<elementname>最低溫度</elementname>
<elementvalue>
<value>21.9</value>
</elementvalue>
</weatherelement>
<weatherelement>
<elementname>最低溫度日期</elementname>
<elementvalue>
<value>12</value>
</elementvalue>
</weatherelement>
<weatherelement>
<elementname>降水量</elementname>
<elementvalue>
<value>244.5</value>
</elementvalue>
</weatherelement>
<weatherelement>
<elementname>最大10分鐘風風速</elementname>
<elementvalue>
<value>9.4</value>
</elementvalue>
</weatherelement>
<weatherelement>
<elementname>最大10分鐘風風向</elementname>
<elementvalue>
<value>360.0</value>
</elementvalue>
</weatherelement>
<weatherelement>
<elementname>最大10分鐘風日期</elementname>
<elementvalue>
<value>15</value>
</elementvalue>
</weatherelement>
<weatherelement>
<elementname>最大瞬間風風速</elementname>
<elementvalue>
<value>16.5</value>
</elementvalue>
</weatherelement>
<weatherelement>
<elementname>最大瞬間風風向</elementname>
<elementvalue>
<value>360.0</value>
</elementvalue>
</weatherelement>
<weatherelement>
<elementname>最大瞬間風日期</elementname>
<elementvalue>
<value>15</value>
</elementvalue>
</weatherelement>
<weatherelement>
<elementname>平均相對濕度</elementname>
<elementvalue>
<value>79</value>
</elementvalue>
</weatherelement>
<weatherelement>
<elementname>最小相對濕度</elementname>
<elementvalue>
<value>48</value>
</elementvalue>
</weatherelement>
<weatherelement>
<elementname>最小相對濕度日期</elementname>
<elementvalue>
<value>28</value>
</elementvalue>
</weatherelement>
<weatherelement>
<elementname>測站氣壓</elementname>
<elementvalue>
<value>1003.2</value>
</elementvalue>
</weatherelement>
<weatherelement>
<elementname>降水日數</elementname>
<elementvalue>
<value>16</value>
</elementvalue>
</weatherelement>
<weatherelement>
<elementname>日照時數</elementname>
<elementvalue>
<value>124.3</value>
</elementvalue>
</weatherelement>
</location>
<location>
<locationname>PENGJIAYU,彭佳嶼</locationname>
<stationid>466950</stationid>
<weatherelement>
<elementname>平均溫度</elementname>
<elementvalue>
<value>26.1</value>
</elementvalue>
</weatherelement>
<weatherelement>
<elementname>最高溫度</elementname>
<elementvalue>
<value>31.7</value>
</elementvalue>
</weatherelement>
<weatherelement>
<elementname>最高溫度日期</elementname>
<elementvalue>
<value>24</value>
</elementvalue>
</weatherelement>
<weatherelement>
<elementname>最低溫度</elementname>
<elementvalue>
<value>20.1</value>
</elementvalue>
</weatherelement>
<weatherelement>
<elementname>最低溫度日期</elementname>
<elementvalue>
<value>1</value>
</elementvalue>
</weatherelement>
<weatherelement>
<elementname>降水量</elementname>
<elementvalue>
<value>69.3</value>
</elementvalue>
</weatherelement>
<weatherelement>
<elementname>最大10分鐘風風速</elementname>
<elementvalue>
<value>15.7</value>
</elementvalue>
</weatherelement>
<weatherelement>
<elementname>最大10分鐘風風向</elementname>
<elementvalue>
<value>270.0</value>
</elementvalue>
</weatherelement>
<weatherelement>
<elementname>最大10分鐘風日期</elementname>
<elementvalue>
<value>19</value>
</elementvalue>
</weatherelement>
<weatherelement>
<elementname>最大瞬間風風速</elementname>
<elementvalue>
<value>21.7</value>
</elementvalue>
</weatherelement>
<weatherelement>
<elementname>最大瞬間風風向</elementname>
<elementvalue>
<value>70.0</value>
</elementvalue>
</weatherelement>
<weatherelement>
<elementname>最大瞬間風日期</elementname>
<elementvalue>
<value>14</value>
</elementvalue>
</weatherelement>
<weatherelement>
<elementname>平均相對濕度</elementname>
<elementvalue>
<value>86</value>
</elementvalue>
</weatherelement>
<weatherelement>
<elementname>最小相對濕度</elementname>
<elementvalue>
<value>62</value>
</elementvalue>
</weatherelement>
<weatherelement>
<elementname>最小相對濕度日期</elementname>
<elementvalue>
<value>12</value>
</elementvalue>
</weatherelement>
<weatherelement>
<elementname>測站氣壓</elementname>
<elementvalue>
<value>995.2</value>
</elementvalue>
</weatherelement>
<weatherelement>
<elementname>降水日數</elementname>
<elementvalue>
<value>7</value>
</elementvalue>
</weatherelement>
<weatherelement>
<elementname>日照時數</elementname>
<elementvalue>
<value>171.4</value>
</elementvalue>
</weatherelement>
</location>
<location>
<locationname>HUALIEN,花蓮</locationname>
<stationid>466990</stationid>
<weatherelement>
<elementname>平均溫度</elementname>
<elementvalue>
<value>27.8</value>
</elementvalue>
</weatherelement>
<weatherelement>
<elementname>最高溫度</elementname>
<elementvalue>
<value>34.1</value>
</elementvalue>
</weatherelement>
<weatherelement>
<elementname>最高溫度日期</elementname>
<elementvalue>
<value>21</value>
</elementvalue>
</weatherelement>
<weatherelement>
<elementname>最低溫度</elementname>
<elementvalue>
<value>23.2</value>
</elementvalue>
</weatherelement>
<weatherelement>
<elementname>最低溫度日期</elementname>
<elementvalue>
<value>1</value>
</elementvalue>
</weatherelement>
<weatherelement>
<elementname>降水量</elementname>
<elementvalue>
<value>122.5</value>
</elementvalue>
</weatherelement>
<weatherelement>
<elementname>最大10分鐘風風速</elementname>
<elementvalue>
<value>11.9</value>
</elementvalue>
</weatherelement>
<weatherelement>
<elementname>最大10分鐘風風向</elementname>
<elementvalue>
<value>200.0</value>
</elementvalue>
</weatherelement>
<weatherelement>
<elementname>最大10分鐘風日期</elementname>
<elementvalue>
<value>18</value>
</elementvalue>
</weatherelement>
<weatherelement>
<elementname>最大瞬間風風速</elementname>
<elementvalue>
<value>17.6</value>
</elementvalue>
</weatherelement>
<weatherelement>
<elementname>最大瞬間風風向</elementname>
<elementvalue>
<value>200.0</value>
</elementvalue>
</weatherelement>
<weatherelement>
<elementname>最大瞬間風日期</elementname>
<elementvalue>
<value>18</value>
</elementvalue>
</weatherelement>
<weatherelement>
<elementname>平均相對濕度</elementname>
<elementvalue>
<value>78</value>
</elementvalue>
</weatherelement>
<weatherelement>
<elementname>最小相對濕度</elementname>
<elementvalue>
<value>51</value>
</elementvalue>
</weatherelement>
<weatherelement>
<elementname>最小相對濕度日期</elementname>
<elementvalue>
<value>12</value>
</elementvalue>
</weatherelement>
<weatherelement>
<elementname>測站氣壓</elementname>
<elementvalue>
<value>1004.0</value>
</elementvalue>
</weatherelement>
<weatherelement>
<elementname>降水日數</elementname>
<elementvalue>
<value>16</value>
</elementvalue>
</weatherelement>
<weatherelement>
<elementname>日照時數</elementname>
<elementvalue>
<value>161.1</value>
</elementvalue>
</weatherelement>
</location>
<location>
<locationname>XINWU,新屋</locationname>
<stationid>467050</stationid>
<weatherelement>
<elementname>平均溫度</elementname>
<elementvalue>
<value>27.4</value>
</elementvalue>
</weatherelement>
<weatherelement>
<elementname>最高溫度</elementname>
<elementvalue>
<value>32.9</value>
</elementvalue>
</weatherelement>
<weatherelement>
<elementname>最高溫度日期</elementname>
<elementvalue>
<value>30</value>
</elementvalue>
</weatherelement>
<weatherelement>
<elementname>最低溫度</elementname>
<elementvalue>
<value>20.9</value>
</elementvalue>
</weatherelement>
<weatherelement>
<elementname>最低溫度日期</elementname>
<elementvalue>
<value>1</value>
</elementvalue>
</weatherelement>
<weatherelement>
<elementname>降水量</elementname>
<elementvalue>
<value>63.7</value>
</elementvalue>
</weatherelement>
<weatherelement>
<elementname>最大10分鐘風風速</elementname>
<elementvalue>
<value>13.0</value>
</elementvalue>
</weatherelement>
<weatherelement>
<elementname>最大10分鐘風風向</elementname>
<elementvalue>
<value>230.0</value>
</elementvalue>
</weatherelement>
<weatherelement>
<elementname>最大10分鐘風日期</elementname>
<elementvalue>
<value>19</value>
</elementvalue>
</weatherelement>
<weatherelement>
<elementname>最大瞬間風風速</elementname>
<elementvalue>
<value>21.7</value>
</elementvalue>
</weatherelement>
<weatherelement>
<elementname>最大瞬間風風向</elementname>
<elementvalue>
<value>220.0</value>
</elementvalue>
</weatherelement>
<weatherelement>
<elementname>最大瞬間風日期</elementname>
<elementvalue>
<value>19</value>
</elementvalue>
</weatherelement>
<weatherelement>
<elementname>平均相對濕度</elementname>
<elementvalue>
<value>80</value>
</elementvalue>
</weatherelement>
<weatherelement>
<elementname>最小相對濕度</elementname>
<elementvalue>
<value>44</value>
</elementvalue>
</weatherelement>
<weatherelement>
<elementname>最小相對濕度日期</elementname>
<elementvalue>
<value>12</value>
</elementvalue>
</weatherelement>
<weatherelement>
<elementname>測站氣壓</elementname>
<elementvalue>
<value>1003.3</value>
</elementvalue>
</weatherelement>
<weatherelement>
<elementname>降水日數</elementname>
<elementvalue>
<value>10</value>
</elementvalue>
</weatherelement>
<weatherelement>
<elementname>日照時數</elementname>
<elementvalue>
<value>175.2</value>
</elementvalue>
</weatherelement>
</location>
<location>
<locationname>SU-AO,蘇澳</locationname>
<stationid>467060</stationid>
<weatherelement>
<elementname>平均溫度</elementname>
<elementvalue>
<value>27.3</value>
</elementvalue>
</weatherelement>
<weatherelement>
<elementname>最高溫度</elementname>
<elementvalue>
<value>34.1</value>
</elementvalue>
</weatherelement>
<weatherelement>
<elementname>最高溫度日期</elementname>
<elementvalue>
<value>7</value>
</elementvalue>
</weatherelement>
<weatherelement>
<elementname>最低溫度</elementname>
<elementvalue>
<value>22.2</value>
</elementvalue>
</weatherelement>
<weatherelement>
<elementname>最低溫度日期</elementname>
<elementvalue>
<value>12</value>
</elementvalue>
</weatherelement>
<weatherelement>
<elementname>降水量</elementname>
<elementvalue>
<value>328.0</value>
</elementvalue>
</weatherelement>
<weatherelement>
<elementname>最大10分鐘風風速</elementname>
<elementvalue>
<value>8.8</value>
</elementvalue>
</weatherelement>
<weatherelement>
<elementname>最大10分鐘風風向</elementname>
<elementvalue>
<value>60.0</value>
</elementvalue>
</weatherelement>
<weatherelement>
<elementname>最大10分鐘風日期</elementname>
<elementvalue>
<value>14</value>
</elementvalue>
</weatherelement>
<weatherelement>
<elementname>最大瞬間風風速</elementname>
<elementvalue>
<value>16.9</value>
</elementvalue>
</weatherelement>
<weatherelement>
<elementname>最大瞬間風風向</elementname>
<elementvalue>
<value>50.0</value>
</elementvalue>
</weatherelement>
<weatherelement>
<elementname>最大瞬間風日期</elementname>
<elementvalue>
<value>14</value>
</elementvalue>
</weatherelement>
<weatherelement>
<elementname>平均相對濕度</elementname>
<elementvalue>
<value>81</value>
</elementvalue>
</weatherelement>
<weatherelement>
<elementname>最小相對濕度</elementname>
<elementvalue>
<value>47</value>
</elementvalue>
</weatherelement>
<weatherelement>
<elementname>最小相對濕度日期</elementname>
<elementvalue>
<value>12</value>
</elementvalue>
</weatherelement>
<weatherelement>
<elementname>測站氣壓</elementname>
<elementvalue>
<value>1003.6</value>
</elementvalue>
</weatherelement>
<weatherelement>
<elementname>降水日數</elementname>
<elementvalue>
<value>15</value>
</elementvalue>
</weatherelement>
<weatherelement>
<elementname>日照時數</elementname>
<elementvalue>
<value>155.8</value>
</elementvalue>
</weatherelement>
</location>
<location>
<locationname>YILAN,宜蘭</locationname>
<stationid>467080</stationid>
<weatherelement>
<elementname>平均溫度</elementname>
<elementvalue>
<value>27.8</value>
</elementvalue>
</weatherelement>
<weatherelement>
<elementname>最高溫度</elementname>
<elementvalue>
<value>34.2</value>
</elementvalue>
</weatherelement>
<weatherelement>
<elementname>最高溫度日期</elementname>
<elementvalue>
<value>9</value>
</elementvalue>
</weatherelement>
<weatherelement>
<elementname>最低溫度</elementname>
<elementvalue>
<value>21.8</value>
</elementvalue>
</weatherelement>
<weatherelement>
<elementname>最低溫度日期</elementname>
<elementvalue>
<value>12</value>
</elementvalue>
</weatherelement>
<weatherelement>
<elementname>降水量</elementname>
<elementvalue>
<value>245.3</value>
</elementvalue>
</weatherelement>
<weatherelement>
<elementname>最大10分鐘風風速</elementname>
<elementvalue>
<value>7.7</value>
</elementvalue>
</weatherelement>
<weatherelement>
<elementname>最大10分鐘風風向</elementname>
<elementvalue>
<value>110.0</value>
</elementvalue>
</weatherelement>
<weatherelement>
<elementname>最大10分鐘風日期</elementname>
<elementvalue>
<value>14</value>
</elementvalue>
</weatherelement>
<weatherelement>
<elementname>最大瞬間風風速</elementname>
<elementvalue>
<value>12.7</value>
</elementvalue>
</weatherelement>
<weatherelement>
<elementname>最大瞬間風風向</elementname>
<elementvalue>
<value>90.0</value>
</elementvalue>
</weatherelement>
<weatherelement>
<elementname>最大瞬間風日期</elementname>
<elementvalue>
<value>14</value>
</elementvalue>
</weatherelement>
<weatherelement>
<elementname>平均相對濕度</elementname>
<elementvalue>
<value>79</value>
</elementvalue>
</weatherelement>
<weatherelement>
<elementname>最小相對濕度</elementname>
<elementvalue>
<value>46</value>
</elementvalue>
</weatherelement>
<weatherelement>
<elementname>最小相對濕度日期</elementname>
<elementvalue>
<value>12</value>
</elementvalue>
</weatherelement>
<weatherelement>
<elementname>測站氣壓</elementname>
<elementvalue>
<value>1005.5</value>
</elementvalue>
</weatherelement>
<weatherelement>
<elementname>降水日數</elementname>
<elementvalue>
<value>16</value>
</elementvalue>
</weatherelement>
<weatherelement>
<elementname>日照時數</elementname>
<elementvalue>
<value>143.8</value>
</elementvalue>
</weatherelement>
</location>
<location>
<locationname>KINMEN,金門</locationname>
<stationid>467110</stationid>
<weatherelement>
<elementname>平均溫度</elementname>
<elementvalue>
<value>27.1</value>
</elementvalue>
</weatherelement>
<weatherelement>
<elementname>最高溫度</elementname>
<elementvalue>
<value>34.1</value>
</elementvalue>
</weatherelement>
<weatherelement>
<elementname>最高溫度日期</elementname>
<elementvalue>
<value>15</value>
</elementvalue>
</weatherelement>
<weatherelement>
<elementname>最低溫度</elementname>
<elementvalue>
<value>21.7</value>
</elementvalue>
</weatherelement>
<weatherelement>
<elementname>最低溫度日期</elementname>
<elementvalue>
<value>2</value>
</elementvalue>
</weatherelement>
<weatherelement>
<elementname>降水量</elementname>
<elementvalue>
<value>109.5</value>
</elementvalue>
</weatherelement>
<weatherelement>
<elementname>最大10分鐘風風速</elementname>
<elementvalue>
<value>12.5</value>
</elementvalue>
</weatherelement>
<weatherelement>
<elementname>最大10分鐘風風向</elementname>
<elementvalue>
<value>230.0</value>
</elementvalue>
</weatherelement>
<weatherelement>
<elementname>最大10分鐘風日期</elementname>
<elementvalue>
<value>19</value>
</elementvalue>
</weatherelement>
<weatherelement>
<elementname>最大瞬間風風速</elementname>
<elementvalue>
<value>22.3</value>
</elementvalue>
</weatherelement>
<weatherelement>
<elementname>最大瞬間風風向</elementname>
<elementvalue>
<value>230.0</value>
</elementvalue>
</weatherelement>
<weatherelement>
<elementname>最大瞬間風日期</elementname>
<elementvalue>
<value>18</value>
</elementvalue>
</weatherelement>
<weatherelement>
<elementname>平均相對濕度</elementname>
<elementvalue>
<value>81</value>
</elementvalue>
</weatherelement>
<weatherelement>
<elementname>最小相對濕度</elementname>
<elementvalue>
<value>41</value>
</elementvalue>
</weatherelement>
<weatherelement>
<elementname>最小相對濕度日期</elementname>
<elementvalue>
<value>16</value>
</elementvalue>
</weatherelement>
<weatherelement>
<elementname>測站氣壓</elementname>
<elementvalue>
<value>1002.8</value>
</elementvalue>
</weatherelement>
<weatherelement>
<elementname>降水日數</elementname>
<elementvalue>
<value>10</value>
</elementvalue>
</weatherelement>
<weatherelement>
<elementname>日照時數</elementname>
<elementvalue>
<value>164.6</value>
</elementvalue>
</weatherelement>
</location>
<location>
<locationname>DONGJIDAO,東吉島</locationname>
<stationid>467300</stationid>
<weatherelement>
<elementname>平均溫度</elementname>
<elementvalue>
<value>28.1</value>
</elementvalue>
</weatherelement>
<weatherelement>
<elementname>最高溫度</elementname>
<elementvalue>
<value>33.4</value>
</elementvalue>
</weatherelement>
<weatherelement>
<elementname>最高溫度日期</elementname>
<elementvalue>
<value>6</value>
</elementvalue>
</weatherelement>
<weatherelement>
<elementname>最低溫度</elementname>
<elementvalue>
<value>24.6</value>
</elementvalue>
</weatherelement>
<weatherelement>
<elementname>最低溫度日期</elementname>
<elementvalue>
<value>19</value>
</elementvalue>
</weatherelement>
<weatherelement>
<elementname>降水量</elementname>
<elementvalue>
<value>343.0</value>
</elementvalue>
</weatherelement>
<weatherelement>
<elementname>最大10分鐘風風速</elementname>
<elementvalue>
<value>17.0</value>
</elementvalue>
</weatherelement>
<weatherelement>
<elementname>最大10分鐘風風向</elementname>
<elementvalue>
<value>30.0</value>
</elementvalue>
</weatherelement>
<weatherelement>
<elementname>最大10分鐘風日期</elementname>
<elementvalue>
<value>15</value>
</elementvalue>
</weatherelement>
<weatherelement>
<elementname>最大瞬間風風速</elementname>
<elementvalue>
<value>23.4</value>
</elementvalue>
</weatherelement>
<weatherelement>
<elementname>最大瞬間風風向</elementname>
<elementvalue>
<value>220.0</value>
</elementvalue>
</weatherelement>
<weatherelement>
<elementname>最大瞬間風日期</elementname>
<elementvalue>
<value>19</value>
</elementvalue>
</weatherelement>
<weatherelement>
<elementname>平均相對濕度</elementname>
<elementvalue>
<value>82</value>
</elementvalue>
</weatherelement>
<weatherelement>
<elementname>最小相對濕度</elementname>
<elementvalue>
<value>65</value>
</elementvalue>
</weatherelement>
<weatherelement>
<elementname>最小相對濕度日期</elementname>
<elementvalue>
<value>16</value>
</elementvalue>
</weatherelement>
<weatherelement>
<elementname>測站氣壓</elementname>
<elementvalue>
<value>1001.4</value>
</elementvalue>
</weatherelement>
<weatherelement>
<elementname>降水日數</elementname>
<elementvalue>
<value>12</value>
</elementvalue>
</weatherelement>
<weatherelement>
<elementname>日照時數</elementname>
<elementvalue>
<value>207.0</value>
</elementvalue>
</weatherelement>
</location>
<location>
<locationname>PENGHU,澎湖</locationname>
<stationid>467350</stationid>
<weatherelement>
<elementname>平均溫度</elementname>
<elementvalue>
<value>28.1</value>
</elementvalue>
</weatherelement>
<weatherelement>
<elementname>最高溫度</elementname>
<elementvalue>
<value>34.4</value>
</elementvalue>
</weatherelement>
<weatherelement>
<elementname>最高溫度日期</elementname>
<elementvalue>
<value>5</value>
</elementvalue>
</weatherelement>
<weatherelement>
<elementname>最低溫度</elementname>
<elementvalue>
<value>24.6</value>
</elementvalue>
</weatherelement>
<weatherelement>
<elementname>最低溫度日期</elementname>
<elementvalue>
<value>19</value>
</elementvalue>
</weatherelement>
<weatherelement>
<elementname>降水量</elementname>
<elementvalue>
<value>116.4</value>
</elementvalue>
</weatherelement>
<weatherelement>
<elementname>最大10分鐘風風速</elementname>
<elementvalue>
<value>8.7</value>
</elementvalue>
</weatherelement>
<weatherelement>
<elementname>最大10分鐘風風向</elementname>
<elementvalue>
<value>190.0</value>
</elementvalue>
</weatherelement>
<weatherelement>
<elementname>最大10分鐘風日期</elementname>
<elementvalue>
<value>18</value>
</elementvalue>
</weatherelement>
<weatherelement>
<elementname>最大瞬間風風速</elementname>
<elementvalue>
<value>17.9</value>
</elementvalue>
</weatherelement>
<weatherelement>
<elementname>最大瞬間風風向</elementname>
<elementvalue>
<value>140.0</value>
</elementvalue>
</weatherelement>
<weatherelement>
<elementname>最大瞬間風日期</elementname>
<elementvalue>
<value>18</value>
</elementvalue>
</weatherelement>
<weatherelement>
<elementname>平均相對濕度</elementname>
<elementvalue>
<value>83</value>
</elementvalue>
</weatherelement>
<weatherelement>
<elementname>最小相對濕度</elementname>
<elementvalue>
<value>57</value>
</elementvalue>
</weatherelement>
<weatherelement>
<elementname>最小相對濕度日期</elementname>
<elementvalue>
<value>12</value>
</elementvalue>
</weatherelement>
<weatherelement>
<elementname>測站氣壓</elementname>
<elementvalue>
<value>1004.7</value>
</elementvalue>
</weatherelement>
<weatherelement>
<elementname>降水日數</elementname>
<elementvalue>
<value>9</value>
</elementvalue>
</weatherelement>
<weatherelement>
<elementname>日照時數</elementname>
<elementvalue>
<value>189.7</value>
</elementvalue>
</weatherelement>
</location>
<location>
<locationname>TAINAN,臺南</locationname>
<stationid>467410</stationid>
<weatherelement>
<elementname>平均溫度</elementname>
<elementvalue>
<value>29.0</value>
</elementvalue>
</weatherelement>
<weatherelement>
<elementname>最高溫度</elementname>
<elementvalue>
<value>35.2</value>
</elementvalue>
</weatherelement>
<weatherelement>
<elementname>最高溫度日期</elementname>
<elementvalue>
<value>5</value>
</elementvalue>
</weatherelement>
<weatherelement>
<elementname>最低溫度</elementname>
<elementvalue>
<value>23.9</value>
</elementvalue>
</weatherelement>
<weatherelement>
<elementname>最低溫度日期</elementname>
<elementvalue>
<value>20</value>
</elementvalue>
</weatherelement>
<weatherelement>
<elementname>降水量</elementname>
<elementvalue>
<value>555.5</value>
</elementvalue>
</weatherelement>
<weatherelement>
<elementname>最大10分鐘風風速</elementname>
<elementvalue>
<value>9.4</value>
</elementvalue>
</weatherelement>
<weatherelement>
<elementname>最大10分鐘風風向</elementname>
<elementvalue>
<value>180.0</value>
</elementvalue>
</weatherelement>
<weatherelement>
<elementname>最大10分鐘風日期</elementname>
<elementvalue>
<value>18</value>
</elementvalue>
</weatherelement>
<weatherelement>
<elementname>最大瞬間風風速</elementname>
<elementvalue>
<value>18.3</value>
</elementvalue>
</weatherelement>
<weatherelement>
<elementname>最大瞬間風風向</elementname>
<elementvalue>
<value>190.0</value>
</elementvalue>
</weatherelement>
<weatherelement>
<elementname>最大瞬間風日期</elementname>
<elementvalue>
<value>18</value>
</elementvalue>
</weatherelement>
<weatherelement>
<elementname>平均相對濕度</elementname>
<elementvalue>
<value>75</value>
</elementvalue>
</weatherelement>
<weatherelement>
<elementname>最小相對濕度</elementname>
<elementvalue>
<value>47</value>
</elementvalue>
</weatherelement>
<weatherelement>
<elementname>最小相對濕度日期</elementname>
<elementvalue>
<value>13</value>
</elementvalue>
</weatherelement>
<weatherelement>
<elementname>測站氣壓</elementname>
<elementvalue>
<value>1003.3</value>
</elementvalue>
</weatherelement>
<weatherelement>
<elementname>降水日數</elementname>
<elementvalue>
<value>15</value>
</elementvalue>
</weatherelement>
<weatherelement>
<elementname>日照時數</elementname>
<elementvalue>
<value>195.8</value>
</elementvalue>
</weatherelement>
</location>
<location>
<locationname>KAOHSIUNG,高雄</locationname>
<stationid>467440</stationid>
<weatherelement>
<elementname>平均溫度</elementname>
<elementvalue>
<value>29.1</value>
</elementvalue>
</weatherelement>
<weatherelement>
<elementname>最高溫度</elementname>
<elementvalue>
<value>34.2</value>
</elementvalue>
</weatherelement>
<weatherelement>
<elementname>最高溫度日期</elementname>
<elementvalue>
<value>8</value>
</elementvalue>
</weatherelement>
<weatherelement>
<elementname>最低溫度</elementname>
<elementvalue>
<value>24.5</value>
</elementvalue>
</weatherelement>
<weatherelement>
<elementname>最低溫度日期</elementname>
<elementvalue>
<value>20</value>
</elementvalue>
</weatherelement>
<weatherelement>
<elementname>降水量</elementname>
<elementvalue>
<value>835.0</value>
</elementvalue>
</weatherelement>
<weatherelement>
<elementname>最大10分鐘風風速</elementname>
<elementvalue>
<value>10.9</value>
</elementvalue>
</weatherelement>
<weatherelement>
<elementname>最大10分鐘風風向</elementname>
<elementvalue>
<value>180.0</value>
</elementvalue>
</weatherelement>
<weatherelement>
<elementname>最大10分鐘風日期</elementname>
<elementvalue>
<value>14</value>
</elementvalue>
</weatherelement>
<weatherelement>
<elementname>最大瞬間風風速</elementname>
<elementvalue>
<value>18.8</value>
</elementvalue>
</weatherelement>
<weatherelement>
<elementname>最大瞬間風風向</elementname>
<elementvalue>
<value>180.0</value>
</elementvalue>
</weatherelement>
<weatherelement>
<elementname>最大瞬間風日期</elementname>
<elementvalue>
<value>14</value>
</elementvalue>
</weatherelement>
<weatherelement>
<elementname>平均相對濕度</elementname>
<elementvalue>
<value>75</value>
</elementvalue>
</weatherelement>
<weatherelement>
<elementname>最小相對濕度</elementname>
<elementvalue>
<value>57</value>
</elementvalue>
</weatherelement>
<weatherelement>
<elementname>最小相對濕度日期</elementname>
<elementvalue>
<value>13</value>
</elementvalue>
</weatherelement>
<weatherelement>
<elementname>測站氣壓</elementname>
<elementvalue>
<value>1005.5</value>
</elementvalue>
</weatherelement>
<weatherelement>
<elementname>降水日數</elementname>
<elementvalue>
<value>14</value>
</elementvalue>
</weatherelement>
<weatherelement>
<elementname>日照時數</elementname>
<elementvalue>
<value>200.8</value>
</elementvalue>
</weatherelement>
</location>
<location>
<locationname>CHIAYI,嘉義</locationname>
<stationid>467480</stationid>
<weatherelement>
<elementname>平均溫度</elementname>
<elementvalue>
<value>28.5</value>
</elementvalue>
</weatherelement>
<weatherelement>
<elementname>最高溫度</elementname>
<elementvalue>
<value>36.7</value>
</elementvalue>
</weatherelement>
<weatherelement>
<elementname>最高溫度日期</elementname>
<elementvalue>
<value>6</value>
</elementvalue>
</weatherelement>
<weatherelement>
<elementname>最低溫度</elementname>
<elementvalue>
<value>23.1</value>
</elementvalue>
</weatherelement>
<weatherelement>
<elementname>最低溫度日期</elementname>
<elementvalue>
<value>28</value>
</elementvalue>
</weatherelement>
<weatherelement>
<elementname>降水量</elementname>
<elementvalue>
<value>428.2</value>
</elementvalue>
</weatherelement>
<weatherelement>
<elementname>最大10分鐘風風速</elementname>
<elementvalue>
<value>7.0</value>
</elementvalue>
</weatherelement>
<weatherelement>
<elementname>最大10分鐘風風向</elementname>
<elementvalue>
<value>250.0</value>
</elementvalue>
</weatherelement>
<weatherelement>
<elementname>最大10分鐘風日期</elementname>
<elementvalue>
<value>23</value>
</elementvalue>
</weatherelement>
<weatherelement>
<elementname>最大瞬間風風速</elementname>
<elementvalue>
<value>12.6</value>
</elementvalue>
</weatherelement>
<weatherelement>
<elementname>最大瞬間風風向</elementname>
<elementvalue>
<value>250.0</value>
</elementvalue>
</weatherelement>
<weatherelement>
<elementname>最大瞬間風日期</elementname>
<elementvalue>
<value>19</value>
</elementvalue>
</weatherelement>
<weatherelement>
<elementname>平均相對濕度</elementname>
<elementvalue>
<value>79</value>
</elementvalue>
</weatherelement>
<weatherelement>
<elementname>最小相對濕度</elementname>
<elementvalue>
<value>45</value>
</elementvalue>
</weatherelement>
<weatherelement>
<elementname>最小相對濕度日期</elementname>
<elementvalue>
<value>6</value>
</elementvalue>
</weatherelement>
<weatherelement>
<elementname>測站氣壓</elementname>
<elementvalue>
<value>1002.6</value>
</elementvalue>
</weatherelement>
<weatherelement>
<elementname>降水日數</elementname>
<elementvalue>
<value>18</value>
</elementvalue>
</weatherelement>
<weatherelement>
<elementname>日照時數</elementname>
<elementvalue>
<value>176.0</value>
</elementvalue>
</weatherelement>
</location>
<location>
<locationname>TAICHUNG,臺中</locationname>
<stationid>467490</stationid>
<weatherelement>
<elementname>平均溫度</elementname>
<elementvalue>
<value>28.7</value>
</elementvalue>
</weatherelement>
<weatherelement>
<elementname>最高溫度</elementname>
<elementvalue>
<value>35.8</value>
</elementvalue>
</weatherelement>
<weatherelement>
<elementname>最高溫度日期</elementname>
<elementvalue>
<value>6</value>
</elementvalue>
</weatherelement>
<weatherelement>
<elementname>最低溫度</elementname>
<elementvalue>
<value>24.0</value>
</elementvalue>
</weatherelement>
<weatherelement>
<elementname>最低溫度日期</elementname>
<elementvalue>
<value>20</value>
</elementvalue>
</weatherelement>
<weatherelement>
<elementname>降水量</elementname>
<elementvalue>
<value>234.0</value>
</elementvalue>
</weatherelement>
<weatherelement>
<elementname>最大10分鐘風風速</elementname>
<elementvalue>
<value>6.4</value>
</elementvalue>
</weatherelement>
<weatherelement>
<elementname>最大10分鐘風風向</elementname>
<elementvalue>
<value>20.0</value>
</elementvalue>
</weatherelement>
<weatherelement>
<elementname>最大10分鐘風日期</elementname>
<elementvalue>
<value>15</value>
</elementvalue>
</weatherelement>
<weatherelement>
<elementname>最大瞬間風風速</elementname>
<elementvalue>
<value>13.4</value>
</elementvalue>
</weatherelement>
<weatherelement>
<elementname>最大瞬間風風向</elementname>
<elementvalue>
<value>40.0</value>
</elementvalue>
</weatherelement>
<weatherelement>
<elementname>最大瞬間風日期</elementname>
<elementvalue>
<value>15</value>
</elementvalue>
</weatherelement>
<weatherelement>
<elementname>平均相對濕度</elementname>
<elementvalue>
<value>76</value>
</elementvalue>
</weatherelement>
<weatherelement>
<elementname>最小相對濕度</elementname>
<elementvalue>
<value>45</value>
</elementvalue>
</weatherelement>
<weatherelement>
<elementname>最小相對濕度日期</elementname>
<elementvalue>
<value>16</value>
</elementvalue>
</weatherelement>
<weatherelement>
<elementname>測站氣壓</elementname>
<elementvalue>
<value>996.0</value>
</elementvalue>
</weatherelement>
<weatherelement>
<elementname>降水日數</elementname>
<elementvalue>
<value>10</value>
</elementvalue>
</weatherelement>
<weatherelement>
<elementname>日照時數</elementname>
<elementvalue>
<value>158.9</value>
</elementvalue>
</weatherelement>
</location>
<location>
<locationname>ALISHAN,阿里山</locationname>
<stationid>467530</stationid>
<weatherelement>
<elementname>平均溫度</elementname>
<elementvalue>
<value>14.4</value>
</elementvalue>
</weatherelement>
<weatherelement>
<elementname>最高溫度</elementname>
<elementvalue>
<value>22.0</value>
</elementvalue>
</weatherelement>
<weatherelement>
<elementname>最高溫度日期</elementname>
<elementvalue>
<value>3</value>
</elementvalue>
</weatherelement>
<weatherelement>
<elementname>最低溫度</elementname>
<elementvalue>
<value>8.2</value>
</elementvalue>
</weatherelement>
<weatherelement>
<elementname>最低溫度日期</elementname>
<elementvalue>
<value>26</value>
</elementvalue>
</weatherelement>
<weatherelement>
<elementname>降水量</elementname>
<elementvalue>
<value>812.3</value>
</elementvalue>
</weatherelement>
<weatherelement>
<elementname>最大10分鐘風風速</elementname>
<elementvalue>
<value>4.5</value>
</elementvalue>
</weatherelement>
<weatherelement>
<elementname>最大10分鐘風風向</elementname>
<elementvalue>
<value>150.0</value>
</elementvalue>
</weatherelement>
<weatherelement>
<elementname>最大10分鐘風日期</elementname>
<elementvalue>
<value>13</value>
</elementvalue>
</weatherelement>
<weatherelement>
<elementname>最大瞬間風風速</elementname>
<elementvalue>
<value>12.1</value>
</elementvalue>
</weatherelement>
<weatherelement>
<elementname>最大瞬間風風向</elementname>
<elementvalue>
<value>150.0</value>
</elementvalue>
</weatherelement>
<weatherelement>
<elementname>最大瞬間風日期</elementname>
<elementvalue>
<value>18</value>
</elementvalue>
</weatherelement>
<weatherelement>
<elementname>平均相對濕度</elementname>
<elementvalue>
<value>96</value>
</elementvalue>
</weatherelement>
<weatherelement>
<elementname>最小相對濕度</elementname>
<elementvalue>
<value>55</value>
</elementvalue>
</weatherelement>
<weatherelement>
<elementname>最小相對濕度日期</elementname>
<elementvalue>
<value>26</value>
</elementvalue>
</weatherelement>
<weatherelement>
<elementname>測站氣壓</elementname>
<elementvalue>
<value>762.5</value>
</elementvalue>
</weatherelement>
<weatherelement>
<elementname>降水日數</elementname>
<elementvalue>
<value>30</value>
</elementvalue>
</weatherelement>
<weatherelement>
<elementname>日照時數</elementname>
<elementvalue>
<value>87.4</value>
</elementvalue>
</weatherelement>
</location>
<location>
<locationname>DAWU,大武</locationname>
<stationid>467540</stationid>
<weatherelement>
<elementname>平均溫度</elementname>
<elementvalue>
<value>28.2</value>
</elementvalue>
</weatherelement>
<weatherelement>
<elementname>最高溫度</elementname>
<elementvalue>
<value>36.7</value>
</elementvalue>
</weatherelement>
<weatherelement>
<elementname>最高溫度日期</elementname>
<elementvalue>
<value>28</value>
</elementvalue>
</weatherelement>
<weatherelement>
<elementname>最低溫度</elementname>
<elementvalue>
<value>23.0</value>
</elementvalue>
</weatherelement>
<weatherelement>
<elementname>最低溫度日期</elementname>
<elementvalue>
<value>16</value>
</elementvalue>
</weatherelement>
<weatherelement>
<elementname>降水量</elementname>
<elementvalue>
<value>490.5</value>
</elementvalue>
</weatherelement>
<weatherelement>
<elementname>最大10分鐘風風速</elementname>
<elementvalue>
<value>7.3</value>
</elementvalue>
</weatherelement>
<weatherelement>
<elementname>最大10分鐘風風向</elementname>
<elementvalue>
<value>30.0</value>
</elementvalue>
</weatherelement>
<weatherelement>
<elementname>最大10分鐘風日期</elementname>
<elementvalue>
<value>16</value>
</elementvalue>
</weatherelement>
<weatherelement>
<elementname>最大瞬間風風速</elementname>
<elementvalue>
<value>12.6</value>
</elementvalue>
</weatherelement>
<weatherelement>
<elementname>最大瞬間風風向</elementname>
<elementvalue>
<value>30.0</value>
</elementvalue>
</weatherelement>
<weatherelement>
<elementname>最大瞬間風日期</elementname>
<elementvalue>
<value>16</value>
</elementvalue>
</weatherelement>
<weatherelement>
<elementname>平均相對濕度</elementname>
<elementvalue>
<value>77</value>
</elementvalue>
</weatherelement>
<weatherelement>
<elementname>最小相對濕度</elementname>
<elementvalue>
<value>46</value>
</elementvalue>
</weatherelement>
<weatherelement>
<elementname>最小相對濕度日期</elementname>
<elementvalue>
<value>28</value>
</elementvalue>
</weatherelement>
<weatherelement>
<elementname>測站氣壓</elementname>
<elementvalue>
<value>1004.9</value>
</elementvalue>
</weatherelement>
<weatherelement>
<elementname>降水日數</elementname>
<elementvalue>
<value>11</value>
</elementvalue>
</weatherelement>
<weatherelement>
<elementname>日照時數</elementname>
<elementvalue>
<value>194.6</value>
</elementvalue>
</weatherelement>
</location>
<location>
<locationname>YUSHAN,玉山</locationname>
<stationid>467550</stationid>
<weatherelement>
<elementname>平均溫度</elementname>
<elementvalue>
<value>8.3</value>
</elementvalue>
</weatherelement>
<weatherelement>
<elementname>最高溫度</elementname>
<elementvalue>
<value>17.7</value>
</elementvalue>
</weatherelement>
<weatherelement>
<elementname>最高溫度日期</elementname>
<elementvalue>
<value>9</value>
</elementvalue>
</weatherelement>
<weatherelement>
<elementname>最低溫度</elementname>
<elementvalue>
<value>2.8</value>
</elementvalue>
</weatherelement>
<weatherelement>
<elementname>最低溫度日期</elementname>
<elementvalue>
<value>11</value>
</elementvalue>
</weatherelement>
<weatherelement>
<elementname>降水量</elementname>
<elementvalue>
<value>429.0</value>
</elementvalue>
</weatherelement>
<weatherelement>
<elementname>最大10分鐘風風速</elementname>
<elementvalue>
<value>18.9</value>
</elementvalue>
</weatherelement>
<weatherelement>
<elementname>最大10分鐘風風向</elementname>
<elementvalue>
<value>200.0</value>
</elementvalue>
</weatherelement>
<weatherelement>
<elementname>最大10分鐘風日期</elementname>
<elementvalue>
<value>18</value>
</elementvalue>
</weatherelement>
<weatherelement>
<elementname>最大瞬間風風速</elementname>
<elementvalue>
<value>26.0</value>
</elementvalue>
</weatherelement>
<weatherelement>
<elementname>最大瞬間風風向</elementname>
<elementvalue>
<value>190.0</value>
</elementvalue>
</weatherelement>
<weatherelement>
<elementname>最大瞬間風日期</elementname>
<elementvalue>
<value>18</value>
</elementvalue>
</weatherelement>
<weatherelement>
<elementname>平均相對濕度</elementname>
<elementvalue>
<value>91</value>
</elementvalue>
</weatherelement>
<weatherelement>
<elementname>最小相對濕度</elementname>
<elementvalue>
<value>21</value>
</elementvalue>
</weatherelement>
<weatherelement>
<elementname>最小相對濕度日期</elementname>
<elementvalue>
<value>9</value>
</elementvalue>
</weatherelement>
<weatherelement>
<elementname>測站氣壓</elementname>
<elementvalue>
<value>642.7</value>
</elementvalue>
</weatherelement>
<weatherelement>
<elementname>降水日數</elementname>
<elementvalue>
<value>23</value>
</elementvalue>
</weatherelement>
<weatherelement>
<elementname>日照時數</elementname>
<elementvalue>
<value>128.8</value>
</elementvalue>
</weatherelement>
</location>
<location>
<locationname>HSINCHU,新竹</locationname>
<stationid>467571</stationid>
<weatherelement>
<elementname>平均溫度</elementname>
<elementvalue>
<value>28.5</value>
</elementvalue>
</weatherelement>
<weatherelement>
<elementname>最高溫度</elementname>
<elementvalue>
<value>36.0</value>
</elementvalue>
</weatherelement>
<weatherelement>
<elementname>最高溫度日期</elementname>
<elementvalue>
<value>8</value>
</elementvalue>
</weatherelement>
<weatherelement>
<elementname>最低溫度</elementname>
<elementvalue>
<value>22.1</value>
</elementvalue>
</weatherelement>
<weatherelement>
<elementname>最低溫度日期</elementname>
<elementvalue>
<value>1</value>
</elementvalue>
</weatherelement>
<weatherelement>
<elementname>降水量</elementname>
<elementvalue>
<value>71.2</value>
</elementvalue>
</weatherelement>
<weatherelement>
<elementname>最大10分鐘風風速</elementname>
<elementvalue>
<value>6.5</value>
</elementvalue>
</weatherelement>
<weatherelement>
<elementname>最大10分鐘風風向</elementname>
<elementvalue>
<value>280.0</value>
</elementvalue>
</weatherelement>
<weatherelement>
<elementname>最大10分鐘風日期</elementname>
<elementvalue>
<value>21</value>
</elementvalue>
</weatherelement>
<weatherelement>
<elementname>最大瞬間風風速</elementname>
<elementvalue>
<value>15.2</value>
</elementvalue>
</weatherelement>
<weatherelement>
<elementname>最大瞬間風風向</elementname>
<elementvalue>
<value>280.0</value>
</elementvalue>
</weatherelement>
<weatherelement>
<elementname>最大瞬間風日期</elementname>
<elementvalue>
<value>23</value>
</elementvalue>
</weatherelement>
<weatherelement>
<elementname>平均相對濕度</elementname>
<elementvalue>
<value>73</value>
</elementvalue>
</weatherelement>
<weatherelement>
<elementname>最小相對濕度</elementname>
<elementvalue>
<value>33</value>
</elementvalue>
</weatherelement>
<weatherelement>
<elementname>最小相對濕度日期</elementname>
<elementvalue>
<value>12</value>
</elementvalue>
</weatherelement>
<weatherelement>
<elementname>測站氣壓</elementname>
<elementvalue>
<value>1002.6</value>
</elementvalue>
</weatherelement>
<weatherelement>
<elementname>降水日數</elementname>
<elementvalue>
<value>9</value>
</elementvalue>
</weatherelement>
<weatherelement>
<elementname>日照時數</elementname>
<elementvalue>
<value>184.6</value>
</elementvalue>
</weatherelement>
</location>
<location>
<locationname>HENGCHUN,恆春</locationname>
<stationid>467590</stationid>
<weatherelement>
<elementname>平均溫度</elementname>
<elementvalue>
<value>28.8</value>
</elementvalue>
</weatherelement>
<weatherelement>
<elementname>最高溫度</elementname>
<elementvalue>
<value>35.7</value>
</elementvalue>
</weatherelement>
<weatherelement>
<elementname>最高溫度日期</elementname>
<elementvalue>
<value>6</value>
</elementvalue>
</weatherelement>
<weatherelement>
<elementname>最低溫度</elementname>
<elementvalue>
<value>24.0</value>
</elementvalue>
</weatherelement>
<weatherelement>
<elementname>最低溫度日期</elementname>
<elementvalue>
<value>16</value>
</elementvalue>
</weatherelement>
<weatherelement>
<elementname>降水量</elementname>
<elementvalue>
<value>488.0</value>
</elementvalue>
</weatherelement>
<weatherelement>
<elementname>最大10分鐘風風速</elementname>
<elementvalue>
<value>8.8</value>
</elementvalue>
</weatherelement>
<weatherelement>
<elementname>最大10分鐘風風向</elementname>
<elementvalue>
<value>30.0</value>
</elementvalue>
</weatherelement>
<weatherelement>
<elementname>最大10分鐘風日期</elementname>
<elementvalue>
<value>13</value>
</elementvalue>
</weatherelement>
<weatherelement>
<elementname>最大瞬間風風速</elementname>
<elementvalue>
<value>17.5</value>
</elementvalue>
</weatherelement>
<weatherelement>
<elementname>最大瞬間風風向</elementname>
<elementvalue>
<value>30.0</value>
</elementvalue>
</weatherelement>
<weatherelement>
<elementname>最大瞬間風日期</elementname>
<elementvalue>
<value>13</value>
</elementvalue>
</weatherelement>
<weatherelement>
<elementname>平均相對濕度</elementname>
<elementvalue>
<value>80</value>
</elementvalue>
</weatherelement>
<weatherelement>
<elementname>最小相對濕度</elementname>
<elementvalue>
<value>36</value>
</elementvalue>
</weatherelement>
<weatherelement>
<elementname>最小相對濕度日期</elementname>
<elementvalue>
<value>12</value>
</elementvalue>
</weatherelement>
<weatherelement>
<elementname>測站氣壓</elementname>
<elementvalue>
<value>1003.6</value>
</elementvalue>
</weatherelement>
<weatherelement>
<elementname>降水日數</elementname>
<elementvalue>
<value>12</value>
</elementvalue>
</weatherelement>
<weatherelement>
<elementname>日照時數</elementname>
<elementvalue>
<value>203.6</value>
</elementvalue>
</weatherelement>
</location>
<location>
<locationname>CHENGGONG,成功</locationname>
<stationid>467610</stationid>
<weatherelement>
<elementname>平均溫度</elementname>
<elementvalue>
<value>27.1</value>
</elementvalue>
</weatherelement>
<weatherelement>
<elementname>最高溫度</elementname>
<elementvalue>
<value>32.8</value>
</elementvalue>
</weatherelement>
<weatherelement>
<elementname>最高溫度日期</elementname>
<elementvalue>
<value>8</value>
</elementvalue>
</weatherelement>
<weatherelement>
<elementname>最低溫度</elementname>
<elementvalue>
<value>22.9</value>
</elementvalue>
</weatherelement>
<weatherelement>
<elementname>最低溫度日期</elementname>
<elementvalue>
<value>16</value>
</elementvalue>
</weatherelement>
<weatherelement>
<elementname>降水量</elementname>
<elementvalue>
<value>216.1</value>
</elementvalue>
</weatherelement>
<weatherelement>
<elementname>最大10分鐘風風速</elementname>
<elementvalue>
<value>7.9</value>
</elementvalue>
</weatherelement>
<weatherelement>
<elementname>最大10分鐘風風向</elementname>
<elementvalue>
<value>190.0</value>
</elementvalue>
</weatherelement>
<weatherelement>
<elementname>最大10分鐘風日期</elementname>
<elementvalue>
<value>23</value>
</elementvalue>
</weatherelement>
<weatherelement>
<elementname>最大瞬間風風速</elementname>
<elementvalue>
<value>16.1</value>
</elementvalue>
</weatherelement>
<weatherelement>
<elementname>最大瞬間風風向</elementname>
<elementvalue>
<value>190.0</value>
</elementvalue>
</weatherelement>
<weatherelement>
<elementname>最大瞬間風日期</elementname>
<elementvalue>
<value>19</value>
</elementvalue>
</weatherelement>
<weatherelement>
<elementname>平均相對濕度</elementname>
<elementvalue>
<value>84</value>
</elementvalue>
</weatherelement>
<weatherelement>
<elementname>最小相對濕度</elementname>
<elementvalue>
<value>40</value>
</elementvalue>
</weatherelement>
<weatherelement>
<elementname>最小相對濕度日期</elementname>
<elementvalue>
<value>12</value>
</elementvalue>
</weatherelement>
<weatherelement>
<elementname>測站氣壓</elementname>
<elementvalue>
<value>1001.5</value>
</elementvalue>
</weatherelement>
<weatherelement>
<elementname>降水日數</elementname>
<elementvalue>
<value>16</value>
</elementvalue>
</weatherelement>
<weatherelement>
<elementname>日照時數</elementname>
<elementvalue>
<value>167.1</value>
</elementvalue>
</weatherelement>
</location>
<location>
<locationname>LANYU,蘭嶼</locationname>
<stationid>467620</stationid>
<weatherelement>
<elementname>平均溫度</elementname>
<elementvalue>
<value>26.0</value>
</elementvalue>
</weatherelement>
<weatherelement>
<elementname>最高溫度</elementname>
<elementvalue>
<value>30.6</value>
</elementvalue>
</weatherelement>
<weatherelement>
<elementname>最高溫度日期</elementname>
<elementvalue>
<value>9</value>
</elementvalue>
</weatherelement>
<weatherelement>
<elementname>最低溫度</elementname>
<elementvalue>
<value>21.0</value>
</elementvalue>
</weatherelement>
<weatherelement>
<elementname>最低溫度日期</elementname>
<elementvalue>
<value>12</value>
</elementvalue>
</weatherelement>
<weatherelement>
<elementname>降水量</elementname>
<elementvalue>
<value>416.0</value>
</elementvalue>
</weatherelement>
<weatherelement>
<elementname>最大10分鐘風風速</elementname>
<elementvalue>
<value>24.3</value>
</elementvalue>
</weatherelement>
<weatherelement>
<elementname>最大10分鐘風風向</elementname>
<elementvalue>
<value>230.0</value>
</elementvalue>
</weatherelement>
<weatherelement>
<elementname>最大10分鐘風日期</elementname>
<elementvalue>
<value>15</value>
</elementvalue>
</weatherelement>
<weatherelement>
<elementname>最大瞬間風風速</elementname>
<elementvalue>
<value>36.7</value>
</elementvalue>
</weatherelement>
<weatherelement>
<elementname>最大瞬間風風向</elementname>
<elementvalue>
<value>220.0</value>
</elementvalue>
</weatherelement>
<weatherelement>
<elementname>最大瞬間風日期</elementname>
<elementvalue>
<value>14</value>
</elementvalue>
</weatherelement>
<weatherelement>
<elementname>平均相對濕度</elementname>
<elementvalue>
<value>86</value>
</elementvalue>
</weatherelement>
<weatherelement>
<elementname>最小相對濕度</elementname>
<elementvalue>
<value>56</value>
</elementvalue>
</weatherelement>
<weatherelement>
<elementname>最小相對濕度日期</elementname>
<elementvalue>
<value>12</value>
</elementvalue>
</weatherelement>
<weatherelement>
<elementname>測站氣壓</elementname>
<elementvalue>
<value>970.0</value>
</elementvalue>
</weatherelement>
<weatherelement>
<elementname>降水日數</elementname>
<elementvalue>
<value>21</value>
</elementvalue>
</weatherelement>
<weatherelement>
<elementname>日照時數</elementname>
<elementvalue>
<value>120.3</value>
</elementvalue>
</weatherelement>
</location>
<location>
<locationname>SUN MOON LAKE,日月潭</locationname>
<stationid>467650</stationid>
<weatherelement>
<elementname>平均溫度</elementname>
<elementvalue>
<value>22.6</value>
</elementvalue>
</weatherelement>
<weatherelement>
<elementname>最高溫度</elementname>
<elementvalue>
<value>31.9</value>
</elementvalue>
</weatherelement>
<weatherelement>
<elementname>最高溫度日期</elementname>
<elementvalue>
<value>5</value>
</elementvalue>
</weatherelement>
<weatherelement>
<elementname>最低溫度</elementname>
<elementvalue>
<value>18.7</value>
</elementvalue>
</weatherelement>
<weatherelement>
<elementname>最低溫度日期</elementname>
<elementvalue>
<value>27</value>
</elementvalue>
</weatherelement>
<weatherelement>
<elementname>降水量</elementname>
<elementvalue>
<value>427.0</value>
</elementvalue>
</weatherelement>
<weatherelement>
<elementname>最大10分鐘風風速</elementname>
<elementvalue>
<value>5.2</value>
</elementvalue>
</weatherelement>
<weatherelement>
<elementname>最大10分鐘風風向</elementname>
<elementvalue>
<value>290.0</value>
</elementvalue>
</weatherelement>
<weatherelement>
<elementname>最大10分鐘風日期</elementname>
<elementvalue>
<value>27</value>
</elementvalue>
</weatherelement>
<weatherelement>
<elementname>最大瞬間風風速</elementname>
<elementvalue>
<value>11.5</value>
</elementvalue>
</weatherelement>
<weatherelement>
<elementname>最大瞬間風風向</elementname>
<elementvalue>
<value>210.0</value>
</elementvalue>
</weatherelement>
<weatherelement>
<elementname>最大瞬間風日期</elementname>
<elementvalue>
<value>19</value>
</elementvalue>
</weatherelement>
<weatherelement>
<elementname>平均相對濕度</elementname>
<elementvalue>
<value>80</value>
</elementvalue>
</weatherelement>
<weatherelement>
<elementname>最小相對濕度</elementname>
<elementvalue>
<value>51</value>
</elementvalue>
</weatherelement>
<weatherelement>
<elementname>最小相對濕度日期</elementname>
<elementvalue>
<value>9</value>
</elementvalue>
</weatherelement>
<weatherelement>
<elementname>測站氣壓</elementname>
<elementvalue>
<value>897.4</value>
</elementvalue>
</weatherelement>
<weatherelement>
<elementname>降水日數</elementname>
<elementvalue>
<value>16</value>
</elementvalue>
</weatherelement>
<weatherelement>
<elementname>日照時數</elementname>
<elementvalue>
<value>106.2</value>
</elementvalue>
</weatherelement>
</location>
<location>
<locationname>TAITUNG,臺東</locationname>
<stationid>467660</stationid>
<weatherelement>
<elementname>平均溫度</elementname>
<elementvalue>
<value>28.3</value>
</elementvalue>
</weatherelement>
<weatherelement>
<elementname>最高溫度</elementname>
<elementvalue>
<value>34.3</value>
</elementvalue>
</weatherelement>
<weatherelement>
<elementname>最高溫度日期</elementname>
<elementvalue>
<value>9</value>
</elementvalue>
</weatherelement>
<weatherelement>
<elementname>最低溫度</elementname>
<elementvalue>
<value>23.7</value>
</elementvalue>
</weatherelement>
<weatherelement>
<elementname>最低溫度日期</elementname>
<elementvalue>
<value>16</value>
</elementvalue>
</weatherelement>
<weatherelement>
<elementname>降水量</elementname>
<elementvalue>
<value>206.2</value>
</elementvalue>
</weatherelement>
<weatherelement>
<elementname>最大10分鐘風風速</elementname>
<elementvalue>
<value>6.4</value>
</elementvalue>
</weatherelement>
<weatherelement>
<elementname>最大10分鐘風風向</elementname>
<elementvalue>
<value>190.0</value>
</elementvalue>
</weatherelement>
<weatherelement>
<elementname>最大10分鐘風日期</elementname>
<elementvalue>
<value>22</value>
</elementvalue>
</weatherelement>
<weatherelement>
<elementname>最大瞬間風風速</elementname>
<elementvalue>
<value>14.3</value>
</elementvalue>
</weatherelement>
<weatherelement>
<elementname>最大瞬間風風向</elementname>
<elementvalue>
<value>200.0</value>
</elementvalue>
</weatherelement>
<weatherelement>
<elementname>最大瞬間風日期</elementname>
<elementvalue>
<value>22</value>
</elementvalue>
</weatherelement>
<weatherelement>
<elementname>平均相對濕度</elementname>
<elementvalue>
<value>81</value>
</elementvalue>
</weatherelement>
<weatherelement>
<elementname>最小相對濕度</elementname>
<elementvalue>
<value>41</value>
</elementvalue>
</weatherelement>
<weatherelement>
<elementname>最小相對濕度日期</elementname>
<elementvalue>
<value>12</value>
</elementvalue>
</weatherelement>
<weatherelement>
<elementname>測站氣壓</elementname>
<elementvalue>
<value>1004.9</value>
</elementvalue>
</weatherelement>
<weatherelement>
<elementname>降水日數</elementname>
<elementvalue>
<value>12</value>
</elementvalue>
</weatherelement>
<weatherelement>
<elementname>日照時數</elementname>
<elementvalue>
<value>189.8</value>
</elementvalue>
</weatherelement>
</location>
<location>
<locationname>WUQI,梧棲</locationname>
<stationid>467770</stationid>
<weatherelement>
<elementname>平均溫度</elementname>
<elementvalue>
<value>28.1</value>
</elementvalue>
</weatherelement>
<weatherelement>
<elementname>最高溫度</elementname>
<elementvalue>
<value>33.2</value>
</elementvalue>
</weatherelement>
<weatherelement>
<elementname>最高溫度日期</elementname>
<elementvalue>
<value>13</value>
</elementvalue>
</weatherelement>
<weatherelement>
<elementname>最低溫度</elementname>
<elementvalue>
<value>22.5</value>
</elementvalue>
</weatherelement>
<weatherelement>
<elementname>最低溫度日期</elementname>
<elementvalue>
<value>2</value>
</elementvalue>
</weatherelement>
<weatherelement>
<elementname>降水量</elementname>
<elementvalue>
<value>69.5</value>
</elementvalue>
</weatherelement>
<weatherelement>
<elementname>最大10分鐘風風速</elementname>
<elementvalue>
<value>16.0</value>
</elementvalue>
</weatherelement>
<weatherelement>
<elementname>最大10分鐘風風向</elementname>
<elementvalue>
<value>360.0</value>
</elementvalue>
</weatherelement>
<weatherelement>
<elementname>最大10分鐘風日期</elementname>
<elementvalue>
<value>15</value>
</elementvalue>
</weatherelement>
<weatherelement>
<elementname>最大瞬間風風速</elementname>
<elementvalue>
<value>25.9</value>
</elementvalue>
</weatherelement>
<weatherelement>
<elementname>最大瞬間風風向</elementname>
<elementvalue>
<value>350.0</value>
</elementvalue>
</weatherelement>
<weatherelement>
<elementname>最大瞬間風日期</elementname>
<elementvalue>
<value>15</value>
</elementvalue>
</weatherelement>
<weatherelement>
<elementname>平均相對濕度</elementname>
<elementvalue>
<value>76</value>
</elementvalue>
</weatherelement>
<weatherelement>
<elementname>最小相對濕度</elementname>
<elementvalue>
<value>46</value>
</elementvalue>
</weatherelement>
<weatherelement>
<elementname>最小相對濕度日期</elementname>
<elementvalue>
<value>12</value>
</elementvalue>
</weatherelement>
<weatherelement>
<elementname>測站氣壓</elementname>
<elementvalue>
<value>1003.0</value>
</elementvalue>
</weatherelement>
<weatherelement>
<elementname>降水日數</elementname>
<elementvalue>
<value>9</value>
</elementvalue>
</weatherelement>
<weatherelement>
<elementname>日照時數</elementname>
<elementvalue>
<value>198.5</value>
</elementvalue>
</weatherelement>
</location>
<location>
<locationname>MATSU,馬祖</locationname>
<stationid>467990</stationid>
<weatherelement>
<elementname>平均溫度</elementname>
<elementvalue>
<value>25.2</value>
</elementvalue>
</weatherelement>
<weatherelement>
<elementname>最高溫度</elementname>
<elementvalue>
<value>32.8</value>
</elementvalue>
</weatherelement>
<weatherelement>
<elementname>最高溫度日期</elementname>
<elementvalue>
<value>27</value>
</elementvalue>
</weatherelement>
<weatherelement>
<elementname>最低溫度</elementname>
<elementvalue>
<value>18.3</value>
</elementvalue>
</weatherelement>
<weatherelement>
<elementname>最低溫度日期</elementname>
<elementvalue>
<value>1</value>
</elementvalue>
</weatherelement>
<weatherelement>
<elementname>降水量</elementname>
<elementvalue>
<value>84.9</value>
</elementvalue>
</weatherelement>
<weatherelement>
<elementname>最大10分鐘風風速</elementname>
<elementvalue>
<value>10.4</value>
</elementvalue>
</weatherelement>
<weatherelement>
<elementname>最大10分鐘風風向</elementname>
<elementvalue>
<value>210.0</value>
</elementvalue>
</weatherelement>
<weatherelement>
<elementname>最大10分鐘風日期</elementname>
<elementvalue>
<value>19</value>
</elementvalue>
</weatherelement>
<weatherelement>
<elementname>最大瞬間風風速</elementname>
<elementvalue>
<value>18.9</value>
</elementvalue>
</weatherelement>
<weatherelement>
<elementname>最大瞬間風風向</elementname>
<elementvalue>
<value>230.0</value>
</elementvalue>
</weatherelement>
<weatherelement>
<elementname>最大瞬間風日期</elementname>
<elementvalue>
<value>19</value>
</elementvalue>
</weatherelement>
<weatherelement>
<elementname>平均相對濕度</elementname>
<elementvalue>
<value>84</value>
</elementvalue>
</weatherelement>
<weatherelement>
<elementname>最小相對濕度</elementname>
<elementvalue>
<value>53</value>
</elementvalue>
</weatherelement>
<weatherelement>
<elementname>最小相對濕度日期</elementname>
<elementvalue>
<value>2</value>
</elementvalue>
</weatherelement>
<weatherelement>
<elementname>測站氣壓</elementname>
<elementvalue>
<value>996.3</value>
</elementvalue>
</weatherelement>
<weatherelement>
<elementname>降水日數</elementname>
<elementvalue>
<value>13</value>
</elementvalue>
</weatherelement>
<weatherelement>
<elementname>日照時數</elementname>
<elementvalue>
<value>143.3</value>
</elementvalue>
</weatherelement>
</location>
</time>
